metabase/__init__.py
metabase/exceptions.py
metabase/mbql/__init__.py
metabase/mbql/aggregations.py
metabase/mbql/base.py
metabase/mbql/filter.py
metabase/mbql/groupby.py
metabase/mbql/query.py
metabase/metabase.py
metabase/missing.py
metabase/resource.py
metabase/resources/__init__.py
metabase/resources/card.py
metabase/resources/database.py
metabase/resources/dataset.py
metabase/resources/field.py
metabase/resources/metric.py
metabase/resources/permission_group.py
metabase/resources/permission_membership.py
metabase/resources/segment.py
metabase/resources/table.py
metabase/resources/user.py
metabase_python-0.3.3.dist-info/LICENSE
metabase_python-0.3.3.dist-info/WHEEL
metabase_python-0.3.3.dist-info/METADATA
metabase_python-0.3.3.dist-info/RECORD
