Metadata-Version: 2.1
Name: metabase-python
Version: 0.3.3
Summary: Python wrapper for interacting with the Metabase API.
Home-page: https://github.com/chasleslr/metabase-python
License: MIT
Author: Charles Lariviere
Requires-Python: >=3.7,<4.0
Classifier: License :: OSI Approved :: MIT License
Classifier: Operating System :: OS Independent
Classifier: Programming Language :: Python :: 3
Classifier: Programming Language :: Python :: 3.10
Classifier: Programming Language :: Python :: 3.7
Classifier: Programming Language :: Python :: 3.8
Classifier: Programming Language :: Python :: 3.9
Requires-Dist: pandas (>=1.0.0,<2.0.0)
Requires-Dist: requests
Project-URL: Repository, https://github.com/chasleslr/metabase-python
